math_proj_sat/__init__.py
math_proj_sat/math_ops.py
tests/__init__.py
tests/test_math_ops.py
math_proj_sat-0.1.1.dist-info/LICENSE
math_proj_sat-0.1.1.dist-info/METADATA
math_proj_sat-0.1.1.dist-info/WHEEL
math_proj_sat-0.1.1.dist-info/top_level.txt
math_proj_sat-0.1.1.dist-info/RECORD
